[
  {
    "categoryName": "Виски",
    "categoryId": "whiskey",
    "items": [
      {
        "title": "Ballantine”s",
        "description": "",
        "price": "54₴",
        "volume": "50мл"
      },
      {
        "title": "Black&White",
        "description": "",
        "price": "40₴",
        "volume": "50мл"
      },
      {
        "title": "William Lawson”s",
        "description": "",
        "price": "40₴",
        "volume": "50мл"
      },
      {
        "title": "Red Label",
        "description": "",
        "price": "70₴",
        "volume": "50мл"
      },
      {
        "title": "Hankey Bannister ",
        "description": "",
        "price": "56₴",
        "volume": "50мл"
      },
      {
        "title": "Jim Beam Cherry",
        "description": "",
        "price": "58₴",
        "volume": "50мл"
      },
      {
        "title": "Jim Beam Apple ",
        "description": "",
        "price": "58₴",
        "volume": "50мл"
      },
      {
        "title": "Jim Beam Honey ",
        "description": "",
        "price": "60₴",
        "volume": "50мл"
      },
      {
        "title": "Jameson ",
        "description": "",
        "price": "60₴",
        "volume": "50мл"
      },
      {
        "title": "Jack Daniels  ",
        "description": "",
        "price": "66₴",
        "volume": "50мл"
      }
    ]
  },
  {
    "categoryName": "Ром",
    "categoryId": "rum",
    "items": [
      {
        "title": "Bacardi Carta Negra",
        "description": "",
        "price": "50₴",
        "volume": "50мл"
      },
      {
        "title": "Captain Morgan Original",
        "description": "",
        "price": "56₴",
        "volume": "50мл"
      },
      {
        "title": "Captain Morgan Caribbean ",
        "description": "",
        "price": "50₴",
        "volume": "50мл"
      },
      {
        "title": "OakHeart",
        "description": "",
        "price": "50₴",
        "volume": "50мл"
      },
      {
        "title": "Малибу ",
        "description": "",
        "price": "43₴",
        "volume": "50мл"
      }
      
    ]
  }
]
